pgsql_upserter/__init__.py
pgsql_upserter/column_matcher.py
pgsql_upserter/config.py
pgsql_upserter/conflict_resolver.py
pgsql_upserter/exceptions.py
pgsql_upserter/schema_inspector.py
pgsql_upserter/temp_staging.py
pgsql_upserter/upsert_engine.py
pgsql_upserter-0.9.3.dist-info/LICENSE
pgsql_upserter-0.9.3.dist-info/METADATA
pgsql_upserter-0.9.3.dist-info/WHEEL
pgsql_upserter-0.9.3.dist-info/RECORD
