Metadata-Version: 2.3
Name: pgsql-upserter
Version: 0.9.3
Summary: PostgreSQL upsert engine using temp tables and automatic conflict resolution
License: MIT
Keywords: postgresql,upsert,database,etl
Author: Joao Brito
Requires-Python: >=3.11,<3.15
Classifier: Development Status :: 4 - Beta
Classifier: Intended Audience :: Developers
Classifier: License :: OSI Approved :: MIT License
Classifier: Programming Language :: Python :: 3
Classifier: Programming Language :: Python :: 3.11
Classifier: Programming Language :: Python :: 3.12
Classifier: Programming Language :: Python :: 3.13
Classifier: Programming Language :: Python :: 3.14
Classifier: Topic :: Database
Classifier: Topic :: Software Development :: Libraries :: Python Modules
Requires-Dist: psycopg2-binary (>=2.9.0)
Requires-Dist: python-dotenv (>=1.0.0)
Project-URL: Homepage, https://github.com/machado000/pgsql-upserter
Project-URL: Issues, https://github.com/machado000/pgsql-upserter/issues
